{
  "fecha_validacion": "2026-07-22T00:36:14",
  "herramienta_utilizada": "src/validar_descargas_fuentes.py",
  "total_fuentes_revisadas": 5,
  "archivos_validos": 4,
  "archivos_con_advertencias": 1,
  "archivos_posiblemente_invalidos": 0,
  "archivos_no_encontrados": 0,
  "resultados_por_fuente": [
    {
      "codigo_fuente": "F02",
      "archivo": "C:\\Users\\monse\\OneDrive\\Desktop\\ProyectoFinal_PoliticasPublicas\\documentos\\fuentes_raw\\F02_seguimiento_al_plan_metropolitano_de_seguridad_y_convivencia_ciudadana_2023-2027.html",
      "tipo_registrado": "text/html",
      "tipo_por_extension": "text/html",
      "archivo_existe": true,
      "tamano_registrado": 196552,
      "tamano_actual": 196552,
      "tamano_coincidente": true,
      "sha256_registrado": "65680fea2a368022218df86068359b3e7b5f695a83673ba0bf0e446921798d47",
      "sha256_actual": "65680fea2a368022218df86068359b3e7b5f695a83673ba0bf0e446921798d47",
      "sha256_coincidente": true,
      "archivo_no_vacio": true,
      "coherencia_tipo_extension": true,
      "archivo_duplicado_entre_fuentes": false,
      "firma_pdf_valida": null,
      "estructura_html_valida": true,
      "texto_visible_no_vacio": true,
      "caracteres_visibles_aprox": 2609,
      "titulo_o_descripcion": "Seguimiento al Plan Metropolitano de Seguridad y Convivencia Ciudadana 2023-2027 – Observatorio Seguridad Accessibility Tools Increase Text Decrease Text Grayscale High Contrast Negative Contrast Light Background Links Underline Readable Font Reset",
      "advertencias": [
        "Se detectaron expresiones asociadas a posibles bloqueos/errores (revisión humana requerida)"
      ],
      "senales_error_detectadas": [
        "\\b404\\b"
      ],
      "estado_tecnico": "Archivo válido con advertencias"
    },
    {
      "codigo_fuente": "F03",
      "archivo": "C:\\Users\\monse\\OneDrive\\Desktop\\ProyectoFinal_PoliticasPublicas\\documentos\\fuentes_raw\\F03_resolución_admq_008-2024.pdf",
      "tipo_registrado": "application/pdf",
      "tipo_por_extension": "application/pdf",
      "archivo_existe": true,
      "tamano_registrado": 606788,
      "tamano_actual": 606788,
      "tamano_coincidente": true,
      "sha256_registrado": "0832e799320deb15ede3475d413cf4cccacce6e27ddb06e7abd11af2b332da85",
      "sha256_actual": "0832e799320deb15ede3475d413cf4cccacce6e27ddb06e7abd11af2b332da85",
      "sha256_coincidente": true,
      "archivo_no_vacio": true,
      "coherencia_tipo_extension": true,
      "archivo_duplicado_entre_fuentes": false,
      "firma_pdf_valida": true,
      "estructura_html_valida": null,
      "texto_visible_no_vacio": null,
      "caracteres_visibles_aprox": null,
      "titulo_o_descripcion": "Archivo PDF (sin extracción de texto en esta etapa)",
      "advertencias": [],
      "senales_error_detectadas": [],
      "estado_tecnico": "Archivo técnicamente válido"
    },
    {
      "codigo_fuente": "F04",
      "archivo": "C:\\Users\\monse\\OneDrive\\Desktop\\ProyectoFinal_PoliticasPublicas\\documentos\\fuentes_raw\\F04_justicia_y_crimen.html",
      "tipo_registrado": "text/html",
      "tipo_por_extension": "text/html",
      "archivo_existe": true,
      "tamano_registrado": 58279,
      "tamano_actual": 58279,
      "tamano_coincidente": true,
      "sha256_registrado": "eb8140d8ec67a9ad5a396d6751bbcec1fda460f57c3e5eb5b3f5ca8d223d34a8",
      "sha256_actual": "eb8140d8ec67a9ad5a396d6751bbcec1fda460f57c3e5eb5b3f5ca8d223d34a8",
      "sha256_coincidente": true,
      "archivo_no_vacio": true,
      "coherencia_tipo_extension": true,
      "archivo_duplicado_entre_fuentes": false,
      "firma_pdf_valida": null,
      "estructura_html_valida": true,
      "texto_visible_no_vacio": true,
      "caracteres_visibles_aprox": 4837,
      "titulo_o_descripcion": "Justicia y crimen |",
      "advertencias": [],
      "senales_error_detectadas": [],
      "estado_tecnico": "Archivo técnicamente válido"
    },
    {
      "codigo_fuente": "F05",
      "archivo": "C:\\Users\\monse\\OneDrive\\Desktop\\ProyectoFinal_PoliticasPublicas\\documentos\\fuentes_raw\\F05_encuesta_de_victimización_y_percepción_de_inseguridad_2011.html",
      "tipo_registrado": "text/html",
      "tipo_por_extension": "text/html",
      "archivo_existe": true,
      "tamano_registrado": 113174,
      "tamano_actual": 113174,
      "tamano_coincidente": true,
      "sha256_registrado": "162f312383b836f156634dd7a85efa0804dde66bde162c9f65b6a4d29b23258a",
      "sha256_actual": "162f312383b836f156634dd7a85efa0804dde66bde162c9f65b6a4d29b23258a",
      "sha256_coincidente": true,
      "archivo_no_vacio": true,
      "coherencia_tipo_extension": true,
      "archivo_duplicado_entre_fuentes": false,
      "firma_pdf_valida": null,
      "estructura_html_valida": true,
      "texto_visible_no_vacio": true,
      "caracteres_visibles_aprox": 44740,
      "titulo_o_descripcion": "Ecuador - Encuesta de Victimización y Percepción de Inseguridad 2011",
      "advertencias": [],
      "senales_error_detectadas": [],
      "estado_tecnico": "Archivo técnicamente válido"
    },
    {
      "codigo_fuente": "F06",
      "archivo": "C:\\Users\\monse\\OneDrive\\Desktop\\ProyectoFinal_PoliticasPublicas\\documentos\\fuentes_raw\\F06_estadísticas_de_emergencias_coordinadas_en_2024.html",
      "tipo_registrado": "text/html",
      "tipo_por_extension": "text/html",
      "archivo_existe": true,
      "tamano_registrado": 73076,
      "tamano_actual": 73076,
      "tamano_coincidente": true,
      "sha256_registrado": "235308c4ae82b9512b71f1c2efe7a53b6699b43644a97947852c146b846c8b2a",
      "sha256_actual": "235308c4ae82b9512b71f1c2efe7a53b6699b43644a97947852c146b846c8b2a",
      "sha256_coincidente": true,
      "archivo_no_vacio": true,
      "coherencia_tipo_extension": true,
      "archivo_duplicado_entre_fuentes": false,
      "firma_pdf_valida": null,
      "estructura_html_valida": true,
      "texto_visible_no_vacio": true,
      "caracteres_visibles_aprox": 8685,
      "titulo_o_descripcion": "El ECU 911 coordinó la atención de más de 3 millones de emergencias en 2024 – Servicio Integrado de Seguridad ECU 911",
      "advertencias": [],
      "senales_error_detectadas": [],
      "estado_tecnico": "Archivo técnicamente válido"
    }
  ],
  "advertencia_metodologica": "La validación técnica comprueba integridad, existencia y formato de los archivos descargados, pero no confirma todavía la autenticidad institucional, vigencia, pertinencia territorial ni exactitud sustantiva de su contenido"
}